hwuncommenter/__init__.py
hwuncommenter/main.py
hwuncommenter-1.0.0.dist-info/licenses/LICENSE
hwuncommenter-1.0.0.dist-info/METADATA
hwuncommenter-1.0.0.dist-info/WHEEL
hwuncommenter-1.0.0.dist-info/entry_points.txt
hwuncommenter-1.0.0.dist-info/top_level.txt
hwuncommenter-1.0.0.dist-info/RECORD
