Metadata-Version: 2.4
Name: hwuncommenter
Version: 1.0.0
Summary: Universal comment remover for any programming language
Home-page: https://github.com/MalikHw47/hwuncommenter
Author: MalikHw47
Author-email: MalikHw47 <Help.malicorporation@gmail.com>
License: MIT
Project-URL: Homepage, https://github.com/MalikHw47/hwuncommenter
Project-URL: Bug Reports, https://github.com/MalikHw47/hwuncommenter/issues
Project-URL: Source, https://github.com/MalikHw47/hwuncommenter
Keywords: comment remover,code cleanup,source code,programming tools
Classifier: Development Status :: 5 - Production/Stable
Classifier: Intended Audience :: Developers
Classifier: License :: OSI Approved :: MIT License
Classifier: Operating System :: OS Independent
Classifier: Programming Language :: Python :: 3
Classifier: Programming Language :: Python :: 3.6
Classifier: Programming Language :: Python :: 3.7
Classifier: Programming Language :: Python :: 3.8
Classifier: Programming Language :: Python :: 3.9
Classifier: Programming Language :: Python :: 3.10
Classifier: Programming Language :: Python :: 3.11
Classifier: Programming Language :: Python :: 3.12
Requires-Python: >=3.6
License-File: LICENSE
Dynamic: author
Dynamic: home-page
Dynamic: license-file
Dynamic: requires-python
